samesyslib/__init__.py
samesyslib/_version.py
samesyslib/db.py
samesyslib/db_config.py
samesyslib/shards.py
samesyslib/utils.py
samesyslib-0.0.42.dist-info/LICENSE
samesyslib-0.0.42.dist-info/METADATA
samesyslib-0.0.42.dist-info/WHEEL
samesyslib-0.0.42.dist-info/top_level.txt
samesyslib-0.0.42.dist-info/RECORD
