Metadata-Version: 2.1
Name: samesyslib
Version: 0.0.42
Summary: Common libs used by SameSystem Data Science team.
Home-page: https://github.com/samesystem-ds/samesyslib
Author: SameSystem
Author-email: linas.ziedas@samesystem.com
Classifier: Programming Language :: Python :: 3
Classifier: License :: OSI Approved :: MIT License
Classifier: Operating System :: OS Independent
Requires-Python: >=3.7
License-File: LICENSE
Requires-Dist: ruamel.yaml
Requires-Dist: sqlalchemy
Requires-Dist: pandas
Requires-Dist: pymysql
Requires-Dist: pydantic
